README.md
license
setup.cfg
setup.py
qfly/__init__.py
qfly/crazyflie.py
qfly/deck.py
qfly/parallel_contexts.py
qfly/pose.py
qfly/qtm.py
qfly/traqr.py
qfly/utils.py
qfly/world.py
qfly.egg-info/PKG-INFO
qfly.egg-info/SOURCES.txt
qfly.egg-info/dependency_links.txt
qfly.egg-info/requires.txt
qfly.egg-info/top_level.txt